psyncf/__init__.py
psyncf/psync.py
psyncf-1.0.0.dist-info/DESCRIPTION.rst
psyncf-1.0.0.dist-info/METADATA
psyncf-1.0.0.dist-info/RECORD
psyncf-1.0.0.dist-info/WHEEL
psyncf-1.0.0.dist-info/entry_points.txt
psyncf-1.0.0.dist-info/metadata.json
psyncf-1.0.0.dist-info/top_level.txt
