Metadata-Version: 2.0
Name: psyncf
Version: 1.0.0
Summary: A script based on rsync for synchronizing files
Home-page: https://github.com/Onway/psync
Author: Onway
Author-email: aluohuai@126.com
License: MIT
Platform: UNKNOWN
Classifier: Development Status :: 5 - Production/Stable
Classifier: Intended Audience :: Developers
Classifier: Environment :: Console
Classifier: License :: OSI Approved :: MIT License
Classifier: Programming Language :: Python :: 2
Classifier: Programming Language :: Python :: 2.7
Classifier: Programming Language :: Python :: 3
Classifier: Programming Language :: Python :: 3.5
Classifier: Programming Language :: Python :: 3.6
